flask_verify/__init__.py
flask_verify/verify_json.py
flask_verify-0.1.2.dist-info/LICENSE
flask_verify-0.1.2.dist-info/WHEEL
flask_verify-0.1.2.dist-info/METADATA
flask_verify-0.1.2.dist-info/RECORD
