Metadata-Version: 2.1
Name: flask_verify
Version: 0.1.2
Summary: Used to verify Flask route Response and Request contents.
Home-page: https://github.com/ambertide/flask-verify
Author: Ege Ozkan
Author-email: egeemirozkan24@gmail.com
Requires-Python: >=3.9
Classifier: License :: OSI Approved :: MIT License
Requires-Dist: flask
